LICENSE
MANIFEST.in
README.rst
setup.py
bee_django_message/__init__.py
bee_django_message/admin.py
bee_django_message/apps.py
bee_django_message/config.py
bee_django_message/decorators.py
bee_django_message/exports.py
bee_django_message/forms.py
bee_django_message/models.py
bee_django_message/signals.py
bee_django_message/tests.py
bee_django_message/urls.py
bee_django_message/utils.py
bee_django_message/views.py
bee_django_message/weixin.py
bee_django_message.egg-info/PKG-INFO
bee_django_message.egg-info/SOURCES.txt
bee_django_message.egg-info/dependency_links.txt
bee_django_message.egg-info/requires.txt
bee_django_message.egg-info/top_level.txt
bee_django_message/migrations/.DS_Store
bee_django_message/migrations/0001_initial.py
bee_django_message/migrations/0001_initial.pyc
bee_django_message/migrations/0002_auto_20181205_2103.py
bee_django_message/migrations/0002_auto_20181205_2103.pyc
bee_django_message/migrations/0003_auto_20181205_2108.py
bee_django_message/migrations/0003_auto_20181205_2108.pyc
bee_django_message/migrations/0004_auto_20181206_1915.py
bee_django_message/migrations/0004_auto_20181206_1915.pyc
bee_django_message/migrations/0005_auto_20181206_1951.py
bee_django_message/migrations/0005_auto_20181206_1951.pyc
bee_django_message/migrations/0006_emailmessage_emailsendrecord_weixinserviceaccesstoken.py
bee_django_message/migrations/0006_emailmessage_emailsendrecord_weixinserviceaccesstoken.pyc
bee_django_message/migrations/0007_auto_20190816_1757.py
bee_django_message/migrations/0007_auto_20190816_1757.pyc
bee_django_message/migrations/0008_auto_20191119_1623.py
bee_django_message/migrations/0008_auto_20191119_1623.pyc
bee_django_message/migrations/0009_auto_20191120_1627.py
bee_django_message/migrations/0009_auto_20191120_1627.pyc
bee_django_message/migrations/0010_auto_20191204_1712.py
bee_django_message/migrations/0010_auto_20191204_1712.pyc
bee_django_message/migrations/__init__.py
bee_django_message/migrations/__init__.pyc
bee_django_message/static/.DS_Store
bee_django_message/static/bee_django_message/bootstrap/css/bootstrap-theme.min.css
bee_django_message/static/bee_django_message/bootstrap/css/bootstrap.min.css
